py_lerchs_grossmann/__about__.py
py_lerchs_grossmann/__init__.py
py_lerchs_grossmann/build_df.py
py_lerchs_grossmann-0.0.15.dist-info/METADATA
py_lerchs_grossmann-0.0.15.dist-info/WHEEL
py_lerchs_grossmann-0.0.15.dist-info/licenses/LICENSE.txt
py_lerchs_grossmann-0.0.15.dist-info/RECORD
