Metadata-Version: 2.4
Name: py-lerchs-grossmann
Version: 0.0.15
Project-URL: Documentation, https://github.com/Mau-Aravena/py-lerchs-grossmann#readme
Project-URL: Issues, https://github.com/Mau-Aravena/py-lerchs-grossmann/issues
Project-URL: Source, https://github.com/Mau-Aravena/py-lerchs-grossmann
Author-email: Mau-Aravena <mau.aravena@outlook.com>
License-Expression: BSD-3-Clause
License-File: LICENSE.txt
Classifier: Development Status :: 4 - Beta
Classifier: Programming Language :: Python :: 3.12
Classifier: Programming Language :: Python :: Implementation :: CPython
Classifier: Programming Language :: Python :: Implementation :: PyPy
Requires-Python: >=3.8
Requires-Dist: numpy
Requires-Dist: pandas
Requires-Dist: pyarrow
